restricted_paths/__init__.py
restricted_paths/middleware.py
restricted_paths/settings.py
django_restricted_paths-1.4.0.dist-info/LICENSE.txt
django_restricted_paths-1.4.0.dist-info/METADATA
django_restricted_paths-1.4.0.dist-info/WHEEL
django_restricted_paths-1.4.0.dist-info/top_level.txt
django_restricted_paths-1.4.0.dist-info/RECORD
