Metadata-Version: 2.1
Name: django-restricted-paths
Version: 1.4.0
Summary: Restricts access to specific urls to staff only by responding with a specific view or raising a 404
Home-page: https://github.com/alexseitsinger/django-restricted-paths
Author: Alex Seitsinger
Author-email: software@alexseitsinger.com
License: BSD 2-Clause License
Project-URL: Documentation, https://github.com/alexseitsinger/django-restricted-paths
Project-URL: Source, https://github.com/alexseitsinger/django-restricted-paths
Project-URL: Tracker, https://github.com/alexseitsinger/django-restricted-paths/issues
Keywords: django,urls
Platform: UNKNOWN
Classifier: Development Status :: 5 - Production/Stable
Classifier: Environment :: Web Environment
Classifier: Framework :: Django
Classifier: Intended Audience :: Developers
Classifier: License :: OSI Approved :: BSD License
Classifier: Natural Language :: English
Classifier: Operating System :: OS Independent
Classifier: Programming Language :: Python :: 2
Classifier: Programming Language :: Python :: 3
Classifier: Topic :: Internet :: WWW/HTTP :: WSGI :: Middleware
Requires-Dist: Django
